{
  "Dataset": {
    "AtomTypeStyle": "chemicalsymbol",
    "Data": [
      {
        "AtomTypes": [
          "Pt",
          "Pt",
          "Pt",
          "Pt",
          "Pt",
          "Pt",
          "Pt",
          "Pt",
          "Pt",
          "Pt",
          "Pt",
          "Pt",
          "Pt",
          "Pt",
          "Pt",
          "Pt",
          "Pt",
          "Pt",
          "Pt",
          "Pt",
          "Pt",
          "Pt",
          "Pt",
          "Pt",
          "Pt",
          "Pt",
          "Pt",
          "Pt",
          "Pt",
          "Pt",
          "Pt",
          "Pt",
          "Pt",
          "Pt",
          "Pt",
          "Pt",
          "Pt",
          "Pt",
          "Pt",
          "Pt",
          "Pt",
          "Pt",
          "Pt",
          "Pt",
          "Pt",
          "Pt",
          "Pt",
          "Pt",
          "Pt",
          "Pt",
          "Pt",
          "Pt",
          "Pt",
          "Pt",
          "Pt",
          "Pt",
          "Pt",
          "Pt",
          "Pt",
          "Pt",
          "Pt",
          "Pt",
          "Pt",
          "Pt",
          "O",
          "O",
          "O"
        ],
        "Energy": -340.11703336,
        "Forces": [
          [
            -0.00046,
            -0.0,
            0.356257
          ],
          [
            0.021773,
            -0.0,
            0.30682
          ],
          [
            0.010079,
            -0.0,
            0.293196
          ],
          [
            -0.075401,
            -0.0,
            0.304798
          ],
          [
            -0.017676,
            -0.003181,
            0.416663
          ],
          [
            -0.017676,
            0.003181,
            0.416663
          ],
          [
            0.020465,
            -0.009741,
            0.420427
          ],
          [
            0.020465,
            0.009741,
            0.420427
          ],
          [
            -0.023364,
            -0.0,
            0.300053
          ],
          [
            0.013408,
            -0.0,
            0.354357
          ],
          [
            0.020726,
            -0.0,
            0.355718
          ],
          [
            0.033015,
            -0.0,
            0.195246
          ],
          [
            0.010563,
            0.000685,
            0.40623
          ],
          [
            0.010563,
            -0.000685,
            0.40623
          ],
          [
            -0.008936,
            0.014456,
            0.403336
          ],
          [
            -0.008936,
            -0.014456,
            0.403336
          ],
          [
            -0.027414,
            -0.020532,
            -0.230108
          ],
          [
            -0.005119,
            -0.011812,
            -0.129617
          ],
          [
            0.033983,
            -0.061501,
            -0.170293
          ],
          [
            0.006181,
            0.026496,
            -0.191335
          ],
          [
            0.020277,
            -0.002325,
            -0.226005
          ],
          [
            -0.027823,
            -0.040438,
            -0.206205
          ],
          [
            -0.027471,
            -0.013425,
            -0.189954
          ],
          [
            0.030841,
            -0.018217,
            -0.216529
          ],
          [
            -0.027414,
            0.020532,
            -0.230108
          ],
          [
            -0.005119,
            0.011812,
            -0.129617
          ],
          [
            0.033983,
            0.061501,
            -0.170293
          ],
          [
            0.006181,
            -0.026496,
            -0.191335
          ],
          [
            0.020277,
            0.002325,
            -0.226005
          ],
          [
            -0.027823,
            0.040438,
            -0.206205
          ],
          [
            -0.027471,
            0.013425,
            -0.189954
          ],
          [
            0.030841,
            0.018217,
            -0.216529
          ],
          [
            -0.001083,
            -0.0,
            -0.665551
          ],
          [
            0.025585,
            -0.0,
            -0.008082
          ],
          [
            -0.004046,
            -0.0,
            0.02233
          ],
          [
            0.173487,
            -0.0,
            -0.253554
          ],
          [
            0.17058,
            -0.0,
            -0.330789
          ],
          [
            -0.182285,
            -0.0,
            -0.314716
          ],
          [
            -0.174591,
            -0.0,
            -0.269719
          ],
          [
            -0.013273,
            -0.0,
            0.037638
          ],
          [
            -0.043406,
            -0.038565,
            0.085162
          ],
          [
            -0.043406,
            0.038565,
            0.085162
          ],
          [
            -0.005973,
            0.101727,
            -0.001002
          ],
          [
            -0.005973,
            -0.101727,
            -0.001002
          ],
          [
            0.009919,
            -0.005444,
            0.121228
          ],
          [
            0.009919,
            0.005444,
            0.121228
          ],
          [
            0.043645,
            -0.047368,
            0.056446
          ],
          [
            0.043645,
            0.047368,
            0.056446
          ],
          [
            -0.267707,
            -2.149376,
            -0.982013
          ],
          [
            -0.035818,
            0.151553,
            -0.280923
          ],
          [
            0.354124,
            0.033047,
            -0.422763
          ],
          [
            0.035093,
            -2.146949,
            -0.907133
          ],
          [
            0.227542,
            -2.13431,
            -0.935439
          ],
          [
            -0.330286,
            0.067464,
            -0.3867
          ],
          [
            -0.318906,
            -0.043369,
            -0.407724
          ],
          [
            0.325024,
            -0.051152,
            -0.408216
          ],
          [
            -0.267707,
            2.149376,
            -0.982013
          ],
          [
            -0.035818,
            -0.151553,
            -0.280923
          ],
          [
            0.354124,
            -0.033047,
            -0.422763
          ],
          [
            0.035093,
            2.146949,
            -0.907133
          ],
          [
            0.227542,
            2.13431,
            -0.935439
          ],
          [
            -0.330286,
            -0.067464,
            -0.3867
          ],
          [
            -0.318906,
            0.043369,
            -0.407724
          ],
          [
            0.325024,
            0.051152,
            -0.408216
          ],
          [
            0.020177,
            -0.0,
            2.646655
          ],
          [
            0.000217,
            -0.0,
            2.77388
          ],
          [
            -0.016784,
            -0.0,
            2.660401
          ]
        ],
        "Lattice": [
          [
            11.285424233,
            0.0,
            0.0
          ],
          [
            0.0,
            11.285424233,
            0.0
          ],
          [
            0.0,
            0.0,
            19.570980073
          ]
        ],
        "NumAtoms": 67,
        "Positions": [
          [
            4.23203,
            1.41068,
            0.0
          ],
          [
            4.23203,
            7.05339,
            0.0
          ],
          [
            9.87475,
            1.41068,
            0.0
          ],
          [
            9.87475,
            7.05339,
            0.0
          ],
          [
            4.23203,
            4.23203,
            0.0
          ],
          [
            4.23203,
            9.87475,
            0.0
          ],
          [
            9.87475,
            4.23203,
            0.0
          ],
          [
            9.87475,
            9.87475,
            0.0
          ],
          [
            1.41068,
            1.41068,
            0.0
          ],
          [
            1.41068,
            7.05339,
            0.0
          ],
          [
            7.05339,
            1.41068,
            0.0
          ],
          [
            7.05339,
            7.05339,
            0.0
          ],
          [
            1.41068,
            4.23203,
            0.0
          ],
          [
            1.41068,
            9.87475,
            0.0
          ],
          [
            7.05339,
            4.23203,
            0.0
          ],
          [
            7.05339,
            9.87475,
            0.0
          ],
          [
            0.0,
            0.0,
            1.99507
          ],
          [
            0.0,
            5.64271,
            1.99507
          ],
          [
            5.64271,
            0.0,
            1.99507
          ],
          [
            5.64271,
            5.64271,
            1.99507
          ],
          [
            2.82136,
            0.0,
            1.99507
          ],
          [
            2.82136,
            5.64271,
            1.99507
          ],
          [
            8.46407,
            0.0,
            1.99507
          ],
          [
            8.46407,
            5.64271,
            1.99507
          ],
          [
            0.0,
            2.82136,
            1.99507
          ],
          [
            0.0,
            8.46407,
            1.99507
          ],
          [
            5.64271,
            2.82136,
            1.99507
          ],
          [
            5.64271,
            8.46407,
            1.99507
          ],
          [
            2.82136,
            2.82136,
            1.99507
          ],
          [
            2.82136,
            8.46407,
            1.99507
          ],
          [
            8.46407,
            2.82136,
            1.99507
          ],
          [
            8.46407,
            8.46407,
            1.99507
          ],
          [
            1.41075,
            1.41068,
            3.98024
          ],
          [
            1.41116,
            7.05339,
            3.99041
          ],
          [
            7.05324,
            1.41068,
            3.99077
          ],
          [
            7.0562,
            7.05339,
            3.98615
          ],
          [
            4.23481,
            1.41068,
            3.98533
          ],
          [
            4.22901,
            7.05339,
            3.98552
          ],
          [
            9.87201,
            1.41068,
            3.98596
          ],
          [
            9.87453,
            7.05339,
            3.99087
          ],
          [
            1.41028,
            4.23057,
            3.99294
          ],
          [
            1.41028,
            9.87621,
            3.99294
          ],
          [
            7.05255,
            4.23358,
            3.9912
          ],
          [
            7.05255,
            9.8732,
            3.9912
          ],
          [
            4.2321,
            4.23191,
            3.9934
          ],
          [
            4.2321,
            9.87487,
            3.9934
          ],
          [
            9.87597,
            4.23092,
            3.9918
          ],
          [
            9.87597,
            9.87586,
            3.9918
          ],
          [
            -0.00346,
            -0.05453,
            5.95562
          ],
          [
            -0.00024,
            5.64307,
            5.9822
          ],
          [
            5.64679,
            -0.00105,
            5.98075
          ],
          [
            5.64298,
            5.58973,
            5.95742
          ],
          [
            2.82449,
            -0.05412,
            5.95635
          ],
          [
            2.81747,
            5.64182,
            5.98102
          ],
          [
            8.46032,
            -0.0006,
            5.98123
          ],
          [
            8.46783,
            5.64195,
            5.98109
          ],
          [
            -0.00346,
            2.87588,
            5.95562
          ],
          [
            -0.00024,
            8.46371,
            5.9822
          ],
          [
            5.64679,
            2.8224,
            5.98075
          ],
          [
            5.64298,
            8.51705,
            5.95742
          ],
          [
            2.82449,
            2.87547,
            5.95635
          ],
          [
            2.81747,
            8.46496,
            5.98102
          ],
          [
            8.46032,
            2.82195,
            5.98123
          ],
          [
            8.46783,
            8.46483,
            5.98109
          ],
          [
            0.0006,
            1.41068,
            7.09231
          ],
          [
            5.64271,
            7.05339,
            7.09172
          ],
          [
            2.82075,
            1.41068,
            7.09211
          ]
        ],
        "Stress": [
          [
            -31.28863,
            0.0,
            -0.04884
          ],
          [
            0.0,
            -23.17786,
            0.0
          ],
          [
            -0.04884,
            0.0,
            -8.64102
          ]
        ],
        "computation_code": "VASP",
        "pseudopotential_information": [
          [
            "PAW_PBE",
            "Pt",
            "04Feb2005"
          ],
          [
            "PAW_PBE",
            "O",
            "08Apr2002"
          ]
        ]
      }
    ],
    "EnergyStyle": "electronvolt",
    "ForcesStyle": "electronvoltperangstrom",
    "LatticeStyle": "angstrom",
    "PositionsStyle": "angstrom",
    "StressStyle": "kB"
  }
}