{
  "Dataset": {
    "AtomTypeStyle": "chemicalsymbol",
    "Data": [
      {
        "AtomTypes": [
          "Pt",
          "Pt",
          "Pt",
          "Pt",
          "Pt",
          "Pt",
          "Pt",
          "Pt",
          "Pt",
          "Pt",
          "Pt",
          "Pt",
          "Pt",
          "Pt",
          "Pt",
          "Pt",
          "Pt",
          "Pt",
          "Pt",
          "Pt",
          "Pt",
          "Pt",
          "Pt",
          "Pt",
          "Pt",
          "Pt",
          "Pt",
          "Pt",
          "Pt",
          "Pt",
          "Pt",
          "Pt",
          "Pt",
          "Pt",
          "Pt",
          "Pt",
          "Pt",
          "Pt",
          "Pt",
          "Pt",
          "Pt",
          "Pt",
          "Pt",
          "Pt",
          "Pt",
          "Pt",
          "Pt",
          "Pt",
          "Pt",
          "Pt",
          "Pt",
          "Pt",
          "Pt",
          "Pt",
          "Pt",
          "Pt",
          "Pt",
          "Pt",
          "Pt",
          "Pt",
          "Pt",
          "Pt",
          "Pt",
          "Pt",
          "O",
          "O"
        ],
        "Energy": -335.35470871,
        "Forces": [
          [
            0.0,
            -0.0,
            0.356643
          ],
          [
            0.0,
            -0.0,
            0.353177
          ],
          [
            0.0,
            -0.0,
            0.301947
          ],
          [
            0.0,
            -0.0,
            0.130754
          ],
          [
            0.0,
            -0.008884,
            0.402472
          ],
          [
            0.0,
            0.008884,
            0.402472
          ],
          [
            0.0,
            0.027704,
            0.369178
          ],
          [
            0.0,
            -0.027704,
            0.369178
          ],
          [
            -0.023411,
            -0.0,
            0.34973
          ],
          [
            -0.093615,
            -0.0,
            0.313949
          ],
          [
            0.023411,
            -0.0,
            0.34973
          ],
          [
            0.093615,
            -0.0,
            0.313949
          ],
          [
            0.034933,
            -0.004453,
            0.401782
          ],
          [
            0.034933,
            0.004453,
            0.401782
          ],
          [
            -0.034933,
            -0.004453,
            0.401782
          ],
          [
            -0.034933,
            0.004453,
            0.401782
          ],
          [
            0.075529,
            -0.029048,
            -0.365057
          ],
          [
            0.066676,
            0.003535,
            -0.386309
          ],
          [
            -0.043183,
            -0.00422,
            -0.265405
          ],
          [
            -0.076106,
            -0.136922,
            -0.236104
          ],
          [
            0.043183,
            -0.00422,
            -0.265405
          ],
          [
            0.076106,
            -0.136922,
            -0.236104
          ],
          [
            -0.075529,
            -0.029048,
            -0.365057
          ],
          [
            -0.066676,
            0.003535,
            -0.386309
          ],
          [
            0.075529,
            0.029048,
            -0.365057
          ],
          [
            0.066676,
            -0.003535,
            -0.386309
          ],
          [
            -0.043183,
            0.00422,
            -0.265405
          ],
          [
            -0.076106,
            0.136922,
            -0.236104
          ],
          [
            0.043183,
            0.00422,
            -0.265405
          ],
          [
            0.076106,
            0.136922,
            -0.236104
          ],
          [
            -0.075529,
            0.029048,
            -0.365057
          ],
          [
            -0.066676,
            -0.003535,
            -0.386309
          ],
          [
            -0.018246,
            -0.0,
            -0.079726
          ],
          [
            0.017178,
            -0.0,
            -0.016648
          ],
          [
            0.018246,
            -0.0,
            -0.079726
          ],
          [
            -0.017178,
            -0.0,
            -0.016648
          ],
          [
            0.0,
            -0.0,
            -0.033716
          ],
          [
            0.0,
            -0.0,
            0.013692
          ],
          [
            0.0,
            -0.0,
            -0.057521
          ],
          [
            0.0,
            -0.0,
            -0.057147
          ],
          [
            0.019143,
            -0.008356,
            -0.028339
          ],
          [
            0.019143,
            0.008356,
            -0.028339
          ],
          [
            -0.019143,
            -0.008356,
            -0.028339
          ],
          [
            -0.019143,
            0.008356,
            -0.028339
          ],
          [
            0.0,
            -0.0024,
            -0.02158
          ],
          [
            0.0,
            0.0024,
            -0.02158
          ],
          [
            0.0,
            0.010284,
            -0.055291
          ],
          [
            0.0,
            -0.010284,
            -0.055291
          ],
          [
            0.048988,
            0.004255,
            0.005888
          ],
          [
            0.006596,
            0.001677,
            -0.015947
          ],
          [
            0.003829,
            0.02945,
            0.001065
          ],
          [
            0.001256,
            -0.031175,
            0.005401
          ],
          [
            -0.003829,
            0.02945,
            0.001065
          ],
          [
            -0.001256,
            -0.031175,
            0.005401
          ],
          [
            -0.048988,
            0.004255,
            0.005888
          ],
          [
            -0.006596,
            0.001677,
            -0.015947
          ],
          [
            0.048988,
            -0.004255,
            0.005888
          ],
          [
            0.006596,
            -0.001677,
            -0.015947
          ],
          [
            0.003829,
            -0.02945,
            0.001065
          ],
          [
            0.001256,
            0.031175,
            0.005401
          ],
          [
            -0.003829,
            -0.02945,
            0.001065
          ],
          [
            -0.001256,
            0.031175,
            0.005401
          ],
          [
            -0.048988,
            -0.004255,
            0.005888
          ],
          [
            -0.006596,
            -0.001677,
            -0.015947
          ],
          [
            -0.047082,
            -0.0,
            5.3e-05
          ],
          [
            0.047082,
            -0.0,
            5.3e-05
          ]
        ],
        "Lattice": [
          [
            11.285424233,
            0.0,
            0.0
          ],
          [
            0.0,
            11.285424233,
            0.0
          ],
          [
            0.0,
            0.0,
            19.570980073
          ]
        ],
        "NumAtoms": 66,
        "Positions": [
          [
            4.23203,
            1.41068,
            0.0
          ],
          [
            4.23203,
            7.05339,
            0.0
          ],
          [
            9.87475,
            1.41068,
            0.0
          ],
          [
            9.87475,
            7.05339,
            0.0
          ],
          [
            4.23203,
            4.23203,
            0.0
          ],
          [
            4.23203,
            9.87475,
            0.0
          ],
          [
            9.87475,
            4.23203,
            0.0
          ],
          [
            9.87475,
            9.87475,
            0.0
          ],
          [
            1.41068,
            1.41068,
            0.0
          ],
          [
            1.41068,
            7.05339,
            0.0
          ],
          [
            7.05339,
            1.41068,
            0.0
          ],
          [
            7.05339,
            7.05339,
            0.0
          ],
          [
            1.41068,
            4.23203,
            0.0
          ],
          [
            1.41068,
            9.87475,
            0.0
          ],
          [
            7.05339,
            4.23203,
            0.0
          ],
          [
            7.05339,
            9.87475,
            0.0
          ],
          [
            0.0,
            0.0,
            1.99507
          ],
          [
            0.0,
            5.64271,
            1.99507
          ],
          [
            5.64271,
            0.0,
            1.99507
          ],
          [
            5.64271,
            5.64271,
            1.99507
          ],
          [
            2.82136,
            0.0,
            1.99507
          ],
          [
            2.82136,
            5.64271,
            1.99507
          ],
          [
            8.46407,
            0.0,
            1.99507
          ],
          [
            8.46407,
            5.64271,
            1.99507
          ],
          [
            0.0,
            2.82136,
            1.99507
          ],
          [
            0.0,
            8.46407,
            1.99507
          ],
          [
            5.64271,
            2.82136,
            1.99507
          ],
          [
            5.64271,
            8.46407,
            1.99507
          ],
          [
            2.82136,
            2.82136,
            1.99507
          ],
          [
            2.82136,
            8.46407,
            1.99507
          ],
          [
            8.46407,
            2.82136,
            1.99507
          ],
          [
            8.46407,
            8.46407,
            1.99507
          ],
          [
            1.43179,
            1.41068,
            3.97655
          ],
          [
            1.40969,
            7.05339,
            3.94926
          ],
          [
            7.03227,
            1.41068,
            3.97655
          ],
          [
            7.05438,
            7.05339,
            3.94926
          ],
          [
            4.23203,
            1.41068,
            3.98933
          ],
          [
            4.23203,
            7.05339,
            3.94441
          ],
          [
            9.87475,
            1.41068,
            3.9269
          ],
          [
            9.87475,
            7.05339,
            3.95713
          ],
          [
            1.42857,
            4.22776,
            3.97843
          ],
          [
            1.42857,
            9.87902,
            3.97843
          ],
          [
            7.0355,
            4.22776,
            3.97843
          ],
          [
            7.0355,
            9.87902,
            3.97843
          ],
          [
            4.23203,
            4.20314,
            4.02644
          ],
          [
            4.23203,
            9.90364,
            4.02644
          ],
          [
            9.87475,
            4.25489,
            3.92918
          ],
          [
            9.87475,
            9.85189,
            3.92918
          ],
          [
            -0.0518,
            -0.01814,
            5.86351
          ],
          [
            -0.01045,
            5.65562,
            5.89804
          ],
          [
            5.7001,
            -0.11464,
            6.00901
          ],
          [
            5.65184,
            5.68295,
            5.91785
          ],
          [
            2.76397,
            -0.11464,
            6.00901
          ],
          [
            2.81223,
            5.68295,
            5.91785
          ],
          [
            8.51587,
            -0.01814,
            5.86351
          ],
          [
            8.47452,
            5.65562,
            5.89804
          ],
          [
            -0.0518,
            2.83949,
            5.86351
          ],
          [
            -0.01045,
            8.45116,
            5.89804
          ],
          [
            5.7001,
            2.936,
            6.00901
          ],
          [
            5.65184,
            8.42383,
            5.91785
          ],
          [
            2.76397,
            2.936,
            6.00901
          ],
          [
            2.81223,
            8.42383,
            5.91785
          ],
          [
            8.51587,
            2.83949,
            5.86351
          ],
          [
            8.47452,
            8.45116,
            5.89804
          ],
          [
            2.79463,
            1.41068,
            7.22407
          ],
          [
            5.66944,
            1.41068,
            7.22407
          ]
        ],
        "Stress": [
          [
            -28.87685,
            0.0,
            0.0
          ],
          [
            0.0,
            -29.42576,
            0.0
          ],
          [
            0.0,
            0.0,
            -9.54967
          ]
        ],
        "computation_code": "VASP",
        "pseudopotential_information": [
          [
            "PAW_PBE",
            "Pt",
            "04Feb2005"
          ],
          [
            "PAW_PBE",
            "O",
            "08Apr2002"
          ]
        ]
      }
    ],
    "EnergyStyle": "electronvolt",
    "ForcesStyle": "electronvoltperangstrom",
    "LatticeStyle": "angstrom",
    "PositionsStyle": "angstrom",
    "StressStyle": "kB"
  }
}