{
  "Dataset": {
    "AtomTypeStyle": "chemicalsymbol",
    "Data": [
      {
        "AtomTypes": [
          "Pt",
          "Pt",
          "Pt",
          "Pt",
          "Pt",
          "Pt",
          "Pt",
          "Pt",
          "Pt",
          "Pt",
          "Pt",
          "Pt",
          "Pt",
          "Pt",
          "Pt",
          "Pt",
          "Pt",
          "Pt",
          "Pt",
          "Pt",
          "Pt",
          "Pt",
          "Pt",
          "Pt",
          "Pt",
          "Pt",
          "Pt",
          "Pt",
          "Pt",
          "Pt",
          "Pt",
          "Pt",
          "Pt",
          "Pt",
          "Pt",
          "Pt",
          "Pt",
          "Pt",
          "Pt",
          "Pt",
          "Pt",
          "Pt",
          "Pt",
          "Pt",
          "Pt",
          "Pt",
          "Pt",
          "Pt",
          "Pt",
          "Pt",
          "Pt",
          "Pt",
          "Pt",
          "Pt",
          "Pt",
          "Pt",
          "Pt",
          "Pt",
          "Pt",
          "Pt",
          "Pt",
          "Pt",
          "Pt",
          "Pt",
          "O",
          "O"
        ],
        "Energy": -335.03345524,
        "Forces": [
          [
            -0.0,
            0.0,
            0.35055
          ],
          [
            -0.0,
            0.0,
            0.348642
          ],
          [
            -0.0,
            0.0,
            0.34845
          ],
          [
            -0.0,
            0.0,
            0.16957
          ],
          [
            -0.0,
            0.003694,
            0.398725
          ],
          [
            -0.0,
            -0.003694,
            0.398725
          ],
          [
            -0.0,
            0.007924,
            0.400905
          ],
          [
            -0.0,
            -0.007924,
            0.400905
          ],
          [
            -0.026668,
            0.0,
            0.359644
          ],
          [
            -0.068505,
            0.0,
            0.324929
          ],
          [
            0.026668,
            0.0,
            0.359644
          ],
          [
            0.068505,
            0.0,
            0.324929
          ],
          [
            0.037299,
            -0.006196,
            0.403161
          ],
          [
            0.037299,
            0.006196,
            0.403161
          ],
          [
            -0.037299,
            -0.006196,
            0.403161
          ],
          [
            -0.037299,
            0.006196,
            0.403161
          ],
          [
            -0.045064,
            -0.034823,
            -0.19183
          ],
          [
            -0.001201,
            0.005882,
            -0.131512
          ],
          [
            0.027409,
            -0.039686,
            -0.236167
          ],
          [
            -0.006571,
            -0.032941,
            -0.121146
          ],
          [
            -0.027409,
            -0.039686,
            -0.236167
          ],
          [
            0.006571,
            -0.032941,
            -0.121146
          ],
          [
            0.045064,
            -0.034823,
            -0.19183
          ],
          [
            0.001201,
            0.005882,
            -0.131512
          ],
          [
            -0.045064,
            0.034823,
            -0.19183
          ],
          [
            -0.001201,
            -0.005882,
            -0.131512
          ],
          [
            0.027409,
            0.039686,
            -0.236167
          ],
          [
            -0.006571,
            0.032941,
            -0.121146
          ],
          [
            -0.027409,
            0.039686,
            -0.236167
          ],
          [
            0.006571,
            0.032941,
            -0.121146
          ],
          [
            0.045064,
            0.034823,
            -0.19183
          ],
          [
            0.001201,
            -0.005882,
            -0.131512
          ],
          [
            -0.065535,
            0.0,
            -0.109014
          ],
          [
            0.001091,
            0.0,
            0.013762
          ],
          [
            0.065535,
            0.0,
            -0.109014
          ],
          [
            -0.001091,
            0.0,
            0.013762
          ],
          [
            -0.0,
            0.0,
            -0.276499
          ],
          [
            -0.0,
            0.0,
            -0.026835
          ],
          [
            -0.0,
            0.0,
            -0.009593
          ],
          [
            -0.0,
            0.0,
            0.073156
          ],
          [
            0.019909,
            -0.030495,
            0.047542
          ],
          [
            0.019909,
            0.030495,
            0.047542
          ],
          [
            -0.019909,
            -0.030495,
            0.047542
          ],
          [
            -0.019909,
            0.030495,
            0.047542
          ],
          [
            -0.0,
            -0.043816,
            0.088082
          ],
          [
            -0.0,
            0.043816,
            0.088082
          ],
          [
            -0.0,
            0.07496,
            -0.056066
          ],
          [
            -0.0,
            -0.07496,
            -0.056066
          ],
          [
            -0.2353,
            -0.053602,
            -0.379065
          ],
          [
            -0.03537,
            0.039336,
            -0.273045
          ],
          [
            0.158273,
            -0.104553,
            0.461996
          ],
          [
            0.031292,
            0.182187,
            -0.244091
          ],
          [
            -0.158273,
            -0.104553,
            0.461996
          ],
          [
            -0.031292,
            0.182187,
            -0.244091
          ],
          [
            0.2353,
            -0.053602,
            -0.379065
          ],
          [
            0.03537,
            0.039336,
            -0.273045
          ],
          [
            -0.2353,
            0.053602,
            -0.379065
          ],
          [
            -0.03537,
            -0.039336,
            -0.273045
          ],
          [
            0.158273,
            0.104553,
            0.461996
          ],
          [
            0.031292,
            -0.182187,
            -0.244091
          ],
          [
            -0.158273,
            0.104553,
            0.461996
          ],
          [
            -0.031292,
            -0.182187,
            -0.244091
          ],
          [
            0.2353,
            0.053602,
            -0.379065
          ],
          [
            0.03537,
            -0.039336,
            -0.273045
          ],
          [
            -0.054831,
            0.0,
            -0.581372
          ],
          [
            0.054831,
            0.0,
            -0.581372
          ]
        ],
        "Lattice": [
          [
            11.285424233,
            0.0,
            0.0
          ],
          [
            0.0,
            11.285424233,
            0.0
          ],
          [
            0.0,
            0.0,
            19.570980073
          ]
        ],
        "NumAtoms": 66,
        "Positions": [
          [
            4.23203,
            1.41068,
            0.0
          ],
          [
            4.23203,
            7.05339,
            0.0
          ],
          [
            9.87475,
            1.41068,
            0.0
          ],
          [
            9.87475,
            7.05339,
            0.0
          ],
          [
            4.23203,
            4.23203,
            0.0
          ],
          [
            4.23203,
            9.87475,
            0.0
          ],
          [
            9.87475,
            4.23203,
            0.0
          ],
          [
            9.87475,
            9.87475,
            0.0
          ],
          [
            1.41068,
            1.41068,
            0.0
          ],
          [
            1.41068,
            7.05339,
            0.0
          ],
          [
            7.05339,
            1.41068,
            0.0
          ],
          [
            7.05339,
            7.05339,
            0.0
          ],
          [
            1.41068,
            4.23203,
            0.0
          ],
          [
            1.41068,
            9.87475,
            0.0
          ],
          [
            7.05339,
            4.23203,
            0.0
          ],
          [
            7.05339,
            9.87475,
            0.0
          ],
          [
            0.0,
            0.0,
            1.99507
          ],
          [
            0.0,
            5.64271,
            1.99507
          ],
          [
            5.64271,
            0.0,
            1.99507
          ],
          [
            5.64271,
            5.64271,
            1.99507
          ],
          [
            2.82136,
            0.0,
            1.99507
          ],
          [
            2.82136,
            5.64271,
            1.99507
          ],
          [
            8.46407,
            0.0,
            1.99507
          ],
          [
            8.46407,
            5.64271,
            1.99507
          ],
          [
            0.0,
            2.82136,
            1.99507
          ],
          [
            0.0,
            8.46407,
            1.99507
          ],
          [
            5.64271,
            2.82136,
            1.99507
          ],
          [
            5.64271,
            8.46407,
            1.99507
          ],
          [
            2.82136,
            2.82136,
            1.99507
          ],
          [
            2.82136,
            8.46407,
            1.99507
          ],
          [
            8.46407,
            2.82136,
            1.99507
          ],
          [
            8.46407,
            8.46407,
            1.99507
          ],
          [
            1.4032,
            1.41068,
            3.98045
          ],
          [
            1.41095,
            7.05339,
            3.99347
          ],
          [
            7.06087,
            1.41068,
            3.98045
          ],
          [
            7.05312,
            7.05339,
            3.99347
          ],
          [
            4.23203,
            1.41068,
            3.96648
          ],
          [
            4.23203,
            7.05339,
            3.9918
          ],
          [
            9.87475,
            1.41068,
            3.99348
          ],
          [
            9.87475,
            7.05339,
            3.99524
          ],
          [
            1.41432,
            4.22833,
            3.99734
          ],
          [
            1.41432,
            9.87845,
            3.99734
          ],
          [
            7.04975,
            4.22833,
            3.99734
          ],
          [
            7.04975,
            9.87845,
            3.99734
          ],
          [
            4.23203,
            4.22694,
            4.00105
          ],
          [
            4.23203,
            9.87984,
            4.00105
          ],
          [
            9.87475,
            4.23376,
            3.9914
          ],
          [
            9.87475,
            9.87302,
            3.9914
          ],
          [
            -0.01008,
            -0.00251,
            5.9715
          ],
          [
            -0.00115,
            5.64398,
            5.97538
          ],
          [
            5.65005,
            -0.06479,
            5.96275
          ],
          [
            5.64333,
            5.64374,
            5.97514
          ],
          [
            2.81401,
            -0.06479,
            5.96275
          ],
          [
            2.82073,
            5.64374,
            5.97514
          ],
          [
            8.47415,
            -0.00251,
            5.9715
          ],
          [
            8.46522,
            5.64398,
            5.97538
          ],
          [
            -0.01008,
            2.82386,
            5.9715
          ],
          [
            -0.00115,
            8.4628,
            5.97538
          ],
          [
            5.65005,
            2.88615,
            5.96275
          ],
          [
            5.64333,
            8.46304,
            5.97514
          ],
          [
            2.81401,
            2.88615,
            5.96275
          ],
          [
            2.82073,
            8.46304,
            5.97514
          ],
          [
            8.47415,
            2.82386,
            5.9715
          ],
          [
            8.46522,
            8.4628,
            5.97538
          ],
          [
            2.8207,
            1.41068,
            7.27943
          ],
          [
            5.64337,
            1.41068,
            7.27943
          ]
        ],
        "Stress": [
          [
            -34.78119,
            0.0,
            0.0
          ],
          [
            0.0,
            -36.47806,
            0.0
          ],
          [
            0.0,
            0.0,
            -17.62889
          ]
        ],
        "computation_code": "VASP",
        "pseudopotential_information": [
          [
            "PAW_PBE",
            "Pt",
            "04Feb2005"
          ],
          [
            "PAW_PBE",
            "O",
            "08Apr2002"
          ]
        ]
      }
    ],
    "EnergyStyle": "electronvolt",
    "ForcesStyle": "electronvoltperangstrom",
    "LatticeStyle": "angstrom",
    "PositionsStyle": "angstrom",
    "StressStyle": "kB"
  }
}